probmods/__init__.py
probmods/_version.py
probmods/bijection.py
probmods/model.py
probmods/test.py
tests/__init__.py
tests/test_bijection.py
tests/test_model.py
tests/test_test.py
tests/util.py
probmods-0.4.1.dist-info/LICENCE.txt
probmods-0.4.1.dist-info/METADATA
probmods-0.4.1.dist-info/WHEEL
probmods-0.4.1.dist-info/top_level.txt
probmods-0.4.1.dist-info/RECORD
