Metadata-Version: 2.1
Name: probmods
Version: 0.4.1
Summary: An interface to facilitate rapid development and deployment of probabilistic models
Home-page: https://github.com/wesselb/probmods
Author: Wessel Bruinsma
Author-email: wessel.p.bruinsma@gmail.com
License: MIT
Requires-Python: >=3.6
License-File: LICENCE.txt
Requires-Dist: numpy (>=1.16)
Requires-Dist: plum-dispatch (>=2)
Requires-Dist: backends
Requires-Dist: backends-matrix
Requires-Dist: varz
